<Properties StartupConfiguration="{739166EA-08A0-47D5-A2DB-085FBEC86EF5}|Default">
  <MonoDevelop.Ide.Workspace ActiveConfiguration="Debug" />
  <MultiItemStartupConfigurations />
  <MonoDevelop.Ide.Workbench ActiveDocument="Views/Confirmation/Login/ConfirmationView.cshtml">
    <Files>
      <File FileName="Views/Confirmation/Login/ConfirmationView.cshtml" Line="16" Column="1" />
    </Files>
    <Pads>
      <Pad Id="ProjectPad">
        <State name="__root__">
          <Node name="Loginnosted">
            <Node name="Loginnosted" expanded="True" />
          </Node>
        </State>
      </Pad>
    </Pads>
  </MonoDevelop.Ide.Workbench>
  <MonoDevelop.Ide.DebuggingService.Breakpoints>
    <BreakpointStore />
  </MonoDevelop.Ide.DebuggingService.Breakpoints>
  <MonoDevelop.Ide.ItemProperties.Loginnosted PreferredExecutionTarget="/System/Volumes/Preboot/Cryptexes/App/System/Applications/Safari.app" />
  <MonoDevelop.Ide.DebuggingService.PinnedWatches />
</Properties>